dataManager/__init__.py
dataManager-0.2.2.dist-info/METADATA
dataManager-0.2.2.dist-info/WHEEL
dataManager-0.2.2.dist-info/top_level.txt
dataManager-0.2.2.dist-info/RECORD
