Metadata-Version: 2.1
Name: dataManager
Version: 0.2.2
Summary: A simple library to simplify data handling in deep learning environments. With an API non dissimilar to PyTorch DataLoader
Home-page: https://github.com/Pensarfeo/DataManager
Author: Pedro A. Favuzzi
Author-email: pa.favuzzi@gmail.com
License: UNKNOWN
Platform: UNKNOWN
Classifier: Programming Language :: Python :: 3
Classifier: License :: OSI Approved :: MIT License
Classifier: Operating System :: OS Independent
